{
  "parent": "thedulling:armageddon",
  "display": {
    "icon": { "item": "thedulling:destroyer_core" },
    "title": { "text": "Destroyer Destroyer" },
    "description": { "text": "Destroy a Destroyer, one of the Dulling's most fearsome beasts." },
    "frame": "challenge",
    "show_toast": true,
    "announce_to_chat": true,
    "hidden": false
  },
  "criteria": {
    "killed_destroyer": {
      "trigger": "minecraft:player_killed_entity",
      "conditions": {
        "entity": { "type": "thedulling:destroyer" }
      }
    }
  }
}